mozart_signal_parser/__init__.py
mozart_signal_parser-0.1.1.dist-info/WHEEL
mozart_signal_parser-0.1.1.dist-info/METADATA
mozart_signal_parser-0.1.1.dist-info/RECORD
